{
	"templateId": "thermal-simple-80mm",
	"fixtureId": "seed-rtl",
	"engine": "thermal",
	"paperWidth": "80mm",
	"html": "<div style=\"width: 48ch; font-family: 'Courier New', Courier, monospace; font-size: 13px; line-height: 1.4; background: #fff; color: #000; padding: 16px 12px; box-shadow: 0 2px 8px rgba(0,0,0,0.12); margin: 0 auto; overflow: hidden; white-space: pre-wrap; word-break: break-all;\"><div style=\"text-align: center\"><strong><span style=\"font-size: 2em; line-height: 1.2\">مخبز ليلى</span></strong><div>طريق الملك عبدالعزيز ٧٧</div><div>+34 555 6569</div></div><hr style=\"border: none; border-top: 1px dashed #000; margin: 4px 0\"><div style=\"display: flex\"><span style=\"flex: 0 0 24ch; text-align: left; overflow: hidden\">5501</span><span style=\"flex: 0 0 24ch; text-align: right; overflow: hidden\">2026-12-27 18:24:00</span></div><hr style=\"border: none; border-top: 1px dashed #000; margin: 4px 0\"><strong>شاي بالنعناع</strong><div style=\"display: flex\"><span style=\"flex: 0 0 6ch; text-align: left; overflow: hidden\">x2</span><span style=\"flex: 0 0 18ch; text-align: left; overflow: hidden\">@ 19.14</span><span style=\"flex: 0 0 24ch; text-align: right; overflow: hidden\">38.28</span></div><strong>تمر مجدول</strong><div style=\"display: flex\"><span style=\"flex: 0 0 6ch; text-align: left; overflow: hidden\">x3</span><span style=\"flex: 0 0 18ch; text-align: left; overflow: hidden\">@ 16.34</span><span style=\"flex: 0 0 24ch; text-align: right; overflow: hidden\">49.02</span></div><strong>قهوة عربية</strong><div style=\"display: flex\"><span style=\"flex: 0 0 6ch; text-align: left; overflow: hidden\">x2</span><span style=\"flex: 0 0 18ch; text-align: left; overflow: hidden\">@ 2.3</span><span style=\"flex: 0 0 24ch; text-align: right; overflow: hidden\">4.6</span></div><hr style=\"border: none; border-top: 1px dashed #000; margin: 4px 0\"><div style=\"display: flex\"><span style=\"flex: 0 0 24ch; text-align: left; overflow: hidden\">Subtotal</span><span style=\"flex: 0 0 24ch; text-align: right; overflow: hidden\">91.9</span></div><div style=\"display: flex\"><span style=\"flex: 0 0 24ch; text-align: left; overflow: hidden\">ضريبة القيمة المضافة 10% (10%)</span><span style=\"flex: 0 0 24ch; text-align: right; overflow: hidden\">8.37</span></div><hr style=\"border: none; border-top: 3px double #000; margin: 4px 0\"><div style=\"display: flex\"><span style=\"flex: 0 0 24ch; text-align: left; overflow: hidden\"><strong>Total</strong></span><span style=\"flex: 0 0 24ch; text-align: right; overflow: hidden\"><strong>91.9</strong></span></div><hr style=\"border: none; border-top: 1px dashed #000; margin: 4px 0\"><div style=\"display: flex\"><span style=\"flex: 0 0 24ch; text-align: left; overflow: hidden\">Cash</span><span style=\"flex: 0 0 24ch; text-align: right; overflow: hidden\">91.9</span></div><div style=\"display: flex\"><span style=\"flex: 0 0 24ch; text-align: left; overflow: hidden\">  Tendered</span><span style=\"flex: 0 0 24ch; text-align: right; overflow: hidden\">95</span></div><div style=\"display: flex\"><span style=\"flex: 0 0 24ch; text-align: left; overflow: hidden\">  Change</span><span style=\"flex: 0 0 24ch; text-align: right; overflow: hidden\">3.1</span></div><div style=\"height: 2.8em\"></div><div style=\"text-align: center\"><div data-barcode-kind=\"barcode\" data-barcode-value=\"5501\" style=\"text-align: center; padding: 8px 0\"><svg viewBox=\"0 0 114 51\" xmlns=\"http://www.w3.org/2000/svg\">\n<path stroke=\"#000000\" stroke-width=\"4\" d=\"M2 35L2 0M40 35L40 0M46 35L46 0M54 35L54 0M60 35L60 0M80 35L80 0M90 35L90 0M112 35L112 0\"></path>\n<path stroke=\"#000000\" stroke-width=\"2\" d=\"M7 35L7 0M31 35L31 0M85 35L85 0M107 35L107 0\"></path>\n<path stroke=\"#000000\" stroke-width=\"6\" d=\"M15 35L15 0M25 35L25 0M69 35L69 0M101 35L101 0\"></path>\n<path d=\"M36.84 49.91Q36.61 49.69 36.61 49.36Q36.61 49.01 36.84 48.78Q37.10 48.56 37.42 48.56Q41.08 48.56 42.14 46.60Q42.47 46.01 42.47 45.47Q42.47 44.20 41.85 43.56Q41.04 42.64 39.00 42.64Q38.44 42.64 37.86 42.69L37.78 42.69Q37.46 42.69 37.21 42.48Q36.97 42.26 36.97 41.95L36.97 41.89L37.22 37.47Q37.26 37.15 37.48 36.95Q37.71 36.74 38.04 36.74L43.17 36.74Q43.52 36.74 43.75 36.98Q43.99 37.21 43.99 37.52Q43.99 37.83 43.73 38.07Q43.50 38.32 43.17 38.32L38.80 38.32L38.65 41.04L39.00 41.04Q41.29 41.04 42.69 42.17Q44.10 43.28 44.10 45.47Q44.10 46.39 43.68 47.19Q43.25 48.00 42.59 48.58Q40.86 50.14 37.42 50.14Q37.10 50.14 36.84 49.91M37.84 42.69Q37.84 42.69 37.86 42.69Q37.86 42.69 37.84 42.69ZM48.84 49.91Q48.61 49.69 48.61 49.36Q48.61 49.01 48.84 48.78Q49.10 48.56 49.42 48.56Q53.08 48.56 54.14 46.60Q54.47 46.01 54.47 45.47Q54.47 44.20 53.85 43.56Q53.04 42.64 51.00 42.64Q50.44 42.64 49.86 42.69L49.78 42.69Q49.46 42.69 49.21 42.48Q48.97 42.26 48.97 41.95L48.97 41.89L49.22 37.47Q49.26 37.15 49.48 36.95Q49.71 36.74 50.04 36.74L55.17 36.74Q55.52 36.74 55.75 36.98Q55.99 37.21 55.99 37.52Q55.99 37.83 55.73 38.07Q55.50 38.32 55.17 38.32L50.80 38.32L50.65 41.04L51.00 41.04Q53.29 41.04 54.69 42.17Q56.10 43.28 56.10 45.47Q56.10 46.39 55.68 47.19Q55.25 48.00 54.59 48.58Q52.86 50.14 49.42 50.14Q49.10 50.14 48.84 49.91M49.84 42.69Q49.84 42.69 49.86 42.69Q49.86 42.69 49.84 42.69ZM64.55 50.14L64.48 50.14Q63.41 50.12 62.62 49.79Q61.82 49.48 61.35 48.98Q60.88 48.45 60.61 47.64Q60.32 46.82 60.23 45.99Q60.14 45.17 60.14 44.06Q60.14 43.07 60.16 42.38Q60.19 41.67 60.30 40.85Q60.41 40.02 60.59 39.46Q60.79 38.89 61.12 38.32Q61.44 37.76 61.89 37.43Q62.35 37.10 63.00 36.89Q63.65 36.68 64.48 36.68Q65.29 36.68 65.94 36.89Q66.59 37.10 67.05 37.43Q67.50 37.76 67.84 38.32Q68.17 38.89 68.35 39.46Q68.55 40.04 68.66 40.85Q68.76 41.67 68.78 42.38Q68.82 43.09 68.82 44.06Q68.82 44.76 68.78 45.33Q68.75 45.89 68.62 46.55Q68.51 47.21 68.33 47.71Q68.15 48.19 67.81 48.66Q67.46 49.13 67.03 49.44Q66.59 49.76 65.96 49.95Q65.33 50.14 64.55 50.14M61.77 42.64L61.77 44.06Q61.77 44.84 61.80 45.40Q61.86 45.96 62.02 46.60Q62.16 47.24 62.45 47.64Q62.74 48.06 63.25 48.33Q63.76 48.59 64.48 48.59L64.86 48.59Q65.37 48.59 65.76 48.40Q66.16 48.19 66.40 47.81Q66.65 47.45 66.81 47.03Q66.97 46.60 67.05 46.06Q67.14 45.50 67.16 45.05Q67.19 44.60 67.19 44.06L67.19 43.26Q67.19 42.73 67.17 42.41Q67.17 42.08 67.16 41.60Q67.14 41.09 67.08 40.82Q67.03 40.52 66.94 40.12Q66.85 39.72 66.70 39.48Q66.56 39.24 66.36 38.98Q66.14 38.72 65.89 38.58Q65.62 38.42 65.26 38.33Q64.91 38.25 64.48 38.25Q64.03 38.25 63.67 38.35Q63.32 38.44 63.05 38.61Q62.78 38.79 62.56 39.05Q62.36 39.29 62.22 39.60Q62.07 39.90 61.98 40.26Q61.89 40.61 61.86 41.01Q61.82 41.39 61.78 41.81Q61.77 42.21 61.77 42.64ZM72.93 40.73Q72.70 40.49 72.70 40.17Q72.70 39.81 72.93 39.64L76.24 36.91Q76.48 36.72 76.77 36.72L77.35 36.72Q77.67 36.72 77.91 36.96Q78.16 37.19 78.16 37.50L78.16 49.31Q78.16 49.62 77.91 49.86Q77.67 50.09 77.35 50.09Q77.02 50.09 76.77 49.86Q76.53 49.64 76.53 49.31L76.53 38.73L74.06 40.76Q73.82 40.96 73.51 40.96Q73.17 40.96 72.93 40.73Z\" fill=\"#000000\"></path>\n</svg>\n</div></div><div style=\"height: 1.4em\"></div><div style=\"text-align: center\"><div>Thank you</div></div><div style=\"border-top: 1px dashed #ccc; margin: 12px 0; position: relative\"><span style=\"position: absolute; top: -8px; left: -4px; font-size: 14px\">✂</span></div></div>",
	"escposHex": "1b 40 1c 2e 1b 4d 00 1b 45 01 1d 21 11 1b 74 20 ea a6 a0 aa 20 e9 ef e9 ee 1d 21 00 1b 45 00 1b 74 20 e1 a9 ef e7 20 9f e9 ea e9 e8 20 e3 a0 a7 9f e9 e3 aa ef aa 20 1b 74 25 b7 b7 0a 0d 1b 74 00 20 20 20 20 20 20 20 20 20 20 20 20 20 20 20 20 20 20 2b 33 34 20 35 35 35 20 36 35 36 39 0a 0d c4 c4 c4 c4 c4 c4 c4 c4 c4 c4 c4 c4 c4 c4 c4 c4 c4 c4 c4 c4 c4 c4 c4 c4 c4 c4 c4 c4 c4 c4 c4 c4 c4 c4 c4 c4 c4 c4 c4 c4 c4 c4 c4 c4 c4 c4 c4 c4 0a 0d 1b 74 00 35 35 30 31 20 20 20 20 20 20 20 20 20 20 20 20 20 20 20 20 20 20 20 20 20 20 20 20 20 32 30 32 36 2d 31 32 2d 32 37 20 31 38 3a 32 34 3a 30 30 0a 0d c4 c4 c4 c4 c4 c4 c4 c4 c4 c4 c4 c4 c4 c4 c4 c4 c4 c4 c4 c4 c4 c4 c4 c4 c4 c4 c4 c4 c4 c4 c4 c4 c4 c4 c4 c4 c4 c4 c4 c4 c4 c4 c4 c4 c4 c4 c4 c4 0a 0d 1b 45 01 1b 74 20 ac 9f ef 20 a0 9f e9 eb e3 eb 9f e3 1b 45 00 0a 0d 1b 74 00 78 32 20 20 20 20 40 20 31 39 2e 31 34 20 20 20 20 20 20 20 20 20 20 20 20 20 20 20 20 20 20 20 20 20 20 20 20 20 20 20 20 20 20 33 38 2e 32 38 0a 0d 1b 45 01 1b 74 20 a2 ea a9 20 ea a4 a7 ed e9 1b 45 00 0a 0d 1b 74 00 78 33 20 20 20 20 40 20 31 36 2e 33 34 20 20 20 20 20 20 20 20 20 20 20 20 20 20 20 20 20 20 20 20 20 20 20 20 20 20 20 20 20 20 34 39 2e 30 32 0a 0d 1b 45 01 1b 74 20 e7 ec ed a1 20 e3 a9 a0 ef a1 1b 45 00 0a 0d 1b 74 00 78 32 20 20 20 20 40 20 32 2e 33 20 20 20 20 20 20 20 20 20 20 20 20 20 20 20 20 20 20 20 20 20 20 20 20 20 20 20 20 20 20 20 20 20 20 34 2e 36 0a 0d c4 c4 c4 c4 c4 c4 c4 c4 c4 c4 c4 c4 c4 c4 c4 c4 c4 c4 c4 c4 c4 c4 c4 c4 c4 c4 c4 c4 c4 c4 c4 c4 c4 c4 c4 c4 c4 c4 c4 c4 c4 c4 c4 c4 c4 c4 c4 c4 0a 0d 1b 74 00 53 75 62 74 6f 74 61 6c 20 20 20 20 20 20 20 20 20 20 20 20 20 20 20 20 20 20 20 20 20 20 20 20 20 20 20 20 20 20 20 20 20 20 20 20 39 31 2e 39 0a 0d 1b 74 20 e0 a9 ef a0 a1 20 9f e9 e7 ef ea a1 20 9f e9 ea e0 9f e5 a1 20 31 30 25 20 20 20 20 20 20 20 20 20 20 20 20 20 20 20 20 20 20 20 20 38 2e 33 37 0a 0d 1b 74 00 28 31 30 25 29 20 20 20 20 20 20 20 20 20 20 20 20 20 20 20 20 20 20 20 20 20 20 20 20 20 20 20 20 20 20 20 20 20 20 20 20 20 20 20 20 20 20 20 0a 0d cd cd cd cd cd cd cd cd cd cd cd cd cd cd cd cd cd cd cd cd cd cd cd cd cd cd cd cd cd cd cd cd cd cd cd cd cd cd cd cd cd cd cd cd cd cd cd cd 0a 0d 1b 74 00 54 6f 74 61 6c 20 20 20 20 20 20 20 20 20 20 20 20 20 20 20 20 20 20 20 20 20 20 20 20 20 20 20 20 20 20 20 20 20 20 20 20 20 20 20 39 31 2e 39 0a 0d c4 c4 c4 c4 c4 c4 c4 c4 c4 c4 c4 c4 c4 c4 c4 c4 c4 c4 c4 c4 c4 c4 c4 c4 c4 c4 c4 c4 c4 c4 c4 c4 c4 c4 c4 c4 c4 c4 c4 c4 c4 c4 c4 c4 c4 c4 c4 c4 0a 0d 1b 74 00 43 61 73 68 20 20 20 20 20 20 20 20 20 20 20 20 20 20 20 20 20 20 20 20 20 20 20 20 20 20 20 20 20 20 20 20 20 20 20 20 20 20 20 20 39 31 2e 39 0a 0d 1b 74 00 54 65 6e 64 65 72 65 64 20 20 20 20 20 20 20 20 20 20 20 20 20 20 20 20 20 20 20 20 20 20 20 20 20 20 20 20 20 20 20 20 20 20 20 20 20 20 39 35 0a 0d 1b 74 00 43 68 61 6e 67 65 20 20 20 20 20 20 20 20 20 20 20 20 20 20 20 20 20 20 20 20 20 20 20 20 20 20 20 20 20 20 20 20 20 20 20 20 20 20 20 33 2e 31 0a 0d 0a 0d 0a 0d 1b 61 01 1d 68 3c 1d 77 03 1d 48 00 1d 6b 49 06 7b 42 35 35 30 31 1b 61 00 0a 0d 0a 0d 1b 74 00 20 20 20 20 20 20 20 20 20 20 20 20 20 20 20 20 20 20 20 54 68 61 6e 6b 20 79 6f 75 0a 0d 1d 56 01 0a 0d"
}
